vector_db_1807/__init__.py
vector_db_1807/async_client.py
vector_db_1807/client.py
vector_db_1807/exceptions.py
vector_db_1807/utils.py
vector_db_1807-0.4.2.dist-info/METADATA
vector_db_1807-0.4.2.dist-info/WHEEL
vector_db_1807-0.4.2.dist-info/licenses/LICENSE
vector_db_1807-0.4.2.dist-info/RECORD
