Metadata-Version: 2.4
Name: vector-db-1807
Version: 0.4.2
Summary: Async + Sync Python SDK for the Vector Database API
Project-URL: Homepage, https://github.com/pravar1919/vector_db_1807
Project-URL: Documentation, https://github.com/pravar1919/vector_db_1807
Author-email: Pravar Sharma <pravar.sharma@gmail.com>
License: MIT
License-File: LICENSE
Requires-Python: >=3.8
Requires-Dist: httpx>=0.27.0
Requires-Dist: requests>=2.31.0
Requires-Dist: testpypi>=1.3.0
